Metadata-Version: 2.1
Name: bababooey
Version: 0.0.1
Summary: the python program to bababooey
Home-page: https://replit.com/@ch1ck3n/bababooey-in-100-lines
Author: ch1ck3n
Author-email: chcknch1ck3n@gmail.com
License: MIT
Platform: UNKNOWN
Classifier: Programming Language :: Python :: 3
Classifier: License :: OSI Approved :: GNU General Public License v3 (GPLv3)
Classifier: Operating System :: OS Independent
Requires-Python: >=3.0
